<?xml version="1.0" encoding="utf-8"?>

<resources>
    <color name="white_24">#0fffffff</color>
    <color name="text_link_color_blue">@*android:color/accent_material_dark</color>
    <color name="pay_in_store_bubble_color">@*android:color/control_checkable_material</color>
    <color name="pay_in_store_theme_color">@*android:color/control_checkable_material</color>
    <color name="gradient_blue_30">@*android:color/control_checkable_material</color>
    <color name="gradient_light_blue">@*android:color/accent_material_dark</color>
    <color name="home_account">@*android:color/button_material_dark</color>

    <color name="home_pay_background_end_color">#ffffffff</color>
    <color name="home_pay_background_start_color">#ffffffff</color>
	
    <color name="menu_account_background_end_color">@*android:color/accent_material_dark</color>
    <color name="menu_account_background_start_color">@*android:color/material_blue_grey_700</color>
    <color name="menu_activity_background_end_color">@*android:color/accent_material_dark</color>
    <color name="menu_activity_background_start_color">@*android:color/material_blue_grey_700</color>
    <color name="menu_balance_background_end_color">@*android:color/accent_material_dark</color>
    <color name="menu_balance_background_start_color">@*android:color/material_blue_grey_700</color>
    <color name="menu_donate_background_end_color">#ff880078</color>
    <color name="menu_donate_background_start_color">#fff00040</color>
    <color name="menu_home_green_background_end_color">@*android:color/accent_material_dark</color>
    <color name="menu_home_green_background_start_color">@*android:color/material_blue_grey_700</color>

    <color name="menu_send_request_background_start_color">@*android:color/control_checkable_material</color>
    <color name="menu_send_request_background_end_color">@*android:color/accessibility_focus_highlight</color>


    <color name="menu_tap_pay_background_end_color">@*android:color/control_checkable_material</color>
    <color name="menu_tap_pay_background_start_color">@*android:color/button_material_dark</color>
    <color name="paypal_credit_background_end_color">@*android:color/control_checkable_material</color>
    <color name="paypal_credit_background_start_color">@*android:color/button_material_dark</color>
    <color name="profile_background_end_color">@*android:color/primary_material_dark</color>
    <color name="profile_background_start_color">@*android:color/control_checkable_material</color>
    <color name="remembered_Login_background_center_color">@*android:color/button_material_dark</color>
    <color name="remembered_login_background">@*android:color/accent_material_dark</color>
    <color name="remembered_login_background_end_color">@*android:color/primary_material_dark</color>
    <color name="remembered_login_background_start_color">@*android:color/button_material_dark</color>


    <color name="request_money_background_start">@*android:color/control_checkable_material</color>	
    <color name="request_money_background_end">@*android:color/accent_material_dark</color>

    <color name="send_money_background_start">@*android:color/control_checkable_material</color>	
    <color name="send_money_background_end">@*android:color/accent_material_dark</color>

	
    <color name="welcome_1_background_end_color">@*android:color/material_blue_grey_700</color>
    <color name="welcome_1_background_start_color">@*android:color/accent_material_dark</color>
    <color name="welcome_2_background_end_color">@*android:color/material_blue_grey_700</color>
    <color name="welcome_2_background_start_color">@*android:color/accent_material_dark</color>
    <color name="welcome_3_background_end_color">#ffde0063</color>
    <color name="welcome_3_background_start_color">#ff640087</color>
    <color name="welcome_4_background_end_color">#ffff9600</color>
    <color name="welcome_4_background_start_color">#ffde0063</color>

    <color name="launch_screen_background_end_color">@*android:color/accent_material_dark</color>
    <color name="launch_screen_background_start_color">@*android:color/primary_material_dark</color>
    <color name="light_blue">@*android:color/accent_material_dark</color>
    <color name="lighter_blue">@*android:color/holo_blue_bright</color>
    <color name="onboarding_activation_request_money">@*android:color/accent_material_dark</color>
    <color name="onboarding_activation_send_money">@*android:color/accent_material_dark</color>
</resources>