<?xml version="1.0" encoding="utf-8"?>
<!--You are editing FX Explorer's Styles-->

<resources>
	<style name="AppBaseThemeDark" parent="@android:style/Theme.Material.NoActionBar" >
		<item name="android:colorPrimaryDark">@*android:color/dim_foreground_light</item>
		<item name="android:editTextStyle">@*nextapp.fx:style/AppDark_EditTextStyle</item>
        <item name="android:statusBarColor">@android:color/transparent</item>
		<item name="android:divider">@null</item>
		<item name="android:windowBackground">@*android:color/background_dark</item>
		<item name="android:navigationBarColor">@*android:color/background_dark</item>
	</style>

	<style name="AppBaseThemeLight" parent="@android:style/Theme.Material.Light.NoActionBar" >
		<item name="android:colorPrimaryDark">@*android:color/timepicker_default_background_material</item>
        <item name="android:statusBarColor">@android:color/transparent</item>
		<item name="android:editTextStyle">@*nextapp.fx:style/AppDark_EditTextStyle</item>
	</style>

	<style name="DialogLight" parent="@android:style/Theme.Material.Light.Dialog">
        <item name="android:windowNoTitle">true</item>
        <item name="android:windowIsFloating">true</item>
        <item name="android:windowIsTranslucent">true</item>
        <item name="android:windowAnimationStyle">@android:style/Animation.Dialog</item>
        <item name="android:backgroundDimEnabled">true</item>
    </style>
    <style name="DialogDark" parent="@android:style/Theme.Material.Dialog">
        <item name="android:windowNoTitle">true</item>
        <item name="android:windowIsFloating">true</item>
        <item name="android:windowIsTranslucent">true</item>
        <item name="android:windowAnimationStyle">@android:style/Animation.Dialog</item>
        <item name="android:backgroundDimEnabled">true</item>
    </style>
    <style name="NotificationText" parent="@android:style/TextAppearance.Material.Notification" />
    <style name="NotificationTitle" parent="@android:style/TextAppearance.Material.Notification.Title" />
</resources>